{
  "entrypoints": [
    "main"
  ],
  "origins": {
    "431": [
      431
    ],
    "754": [
      754
    ],
    "17896441": [
      869,
      401
    ],
    "main": [
      354,
      869,
      792
    ],
    "runtime~main": [
      792,
      869,
      354
    ],
    "0058b4c6": [
      849
    ],
    "009f1e98": [
      715
    ],
    "0e384e19": [
      976
    ],
    "10171e00": [
      542
    ],
    "182222c5": [
      440
    ],
    "2e4bcb17": [
      913
    ],
    "3d44d291": [
      922
    ],
    "4d54d076": [
      459
    ],
    "54f44165": [
      924
    ],
    "56daa205": [
      839
    ],
    "5d45c52a": [
      578
    ],
    "5e95c892": [
      647
    ],
    "68a6b4c1": [
      158
    ],
    "6d15685b": [
      288
    ],
    "9432f635": [
      163
    ],
    "a7bd4aaa": [
      98
    ],
    "a94703ab": [
      869,
      48
    ],
    "aba21aa0": [
      742
    ],
    "aef2f35b": [
      365
    ],
    "be2d6cb8": [
      681
    ],
    "c98dd9d0": [
      854
    ],
    "eada5a75": [
      678
    ],
    "fbd7a87c": [
      361
    ],
    "styles": [
      48,
      354,
      401,
      792,
      869
    ]
  },
  "assets": {
    "48": {
      "js": [
        {
          "file": "assets/js/a94703ab.73cafc89.js",
          "hash": "b96da1010608cedd",
          "publicPath": "/assets/js/a94703ab.73cafc89.js"
        }
      ]
    },
    "98": {
      "js": [
        {
          "file": "assets/js/a7bd4aaa.9d3708c4.js",
          "hash": "0745cb3d4e43510f",
          "publicPath": "/assets/js/a7bd4aaa.9d3708c4.js"
        }
      ]
    },
    "158": {
      "js": [
        {
          "file": "assets/js/68a6b4c1.962edfe5.js",
          "hash": "1ebec5efd319d5c7",
          "publicPath": "/assets/js/68a6b4c1.962edfe5.js"
        }
      ]
    },
    "163": {
      "js": [
        {
          "file": "assets/js/9432f635.bbcd4114.js",
          "hash": "41e896e630a6fa2e",
          "publicPath": "/assets/js/9432f635.bbcd4114.js"
        }
      ]
    },
    "288": {
      "js": [
        {
          "file": "assets/js/6d15685b.c80cc285.js",
          "hash": "a2d9b4b8e9141fb8",
          "publicPath": "/assets/js/6d15685b.c80cc285.js"
        }
      ]
    },
    "354": {
      "js": [
        {
          "file": "assets/js/runtime~main.e4e2d744.js",
          "hash": "09ed964749c6fe26",
          "publicPath": "/assets/js/runtime~main.e4e2d744.js"
        }
      ]
    },
    "361": {
      "js": [
        {
          "file": "assets/js/fbd7a87c.1906b91b.js",
          "hash": "cd540cb6a265f14f",
          "publicPath": "/assets/js/fbd7a87c.1906b91b.js"
        }
      ]
    },
    "365": {
      "js": [
        {
          "file": "assets/js/aef2f35b.75e1c8b2.js",
          "hash": "8b5a43d0c0f0ac99",
          "publicPath": "/assets/js/aef2f35b.75e1c8b2.js"
        }
      ]
    },
    "401": {
      "js": [
        {
          "file": "assets/js/17896441.01531c11.js",
          "hash": "a47c8fef956d3b43",
          "publicPath": "/assets/js/17896441.01531c11.js"
        }
      ]
    },
    "431": {
      "js": [
        {
          "file": "assets/js/431.7ea2e2c4.js",
          "hash": "1462eeb69ba300c7",
          "publicPath": "/assets/js/431.7ea2e2c4.js"
        }
      ]
    },
    "440": {
      "js": [
        {
          "file": "assets/js/182222c5.2d794f17.js",
          "hash": "9092d89b282edb11",
          "publicPath": "/assets/js/182222c5.2d794f17.js"
        }
      ]
    },
    "459": {
      "js": [
        {
          "file": "assets/js/4d54d076.6b270ee6.js",
          "hash": "80ae6f91f0e32c64",
          "publicPath": "/assets/js/4d54d076.6b270ee6.js"
        }
      ]
    },
    "542": {
      "js": [
        {
          "file": "assets/js/10171e00.0f5fcc89.js",
          "hash": "c421a46b3c052551",
          "publicPath": "/assets/js/10171e00.0f5fcc89.js"
        }
      ]
    },
    "578": {
      "js": [
        {
          "file": "assets/js/5d45c52a.4a0d461f.js",
          "hash": "0b895c970cbe5174",
          "publicPath": "/assets/js/5d45c52a.4a0d461f.js"
        }
      ]
    },
    "647": {
      "js": [
        {
          "file": "assets/js/5e95c892.0532531f.js",
          "hash": "4ff14e8ce8c960ea",
          "publicPath": "/assets/js/5e95c892.0532531f.js"
        }
      ]
    },
    "678": {
      "js": [
        {
          "file": "assets/js/eada5a75.fdbbfa2b.js",
          "hash": "5e12d55500f5a987",
          "publicPath": "/assets/js/eada5a75.fdbbfa2b.js"
        }
      ]
    },
    "681": {
      "js": [
        {
          "file": "assets/js/be2d6cb8.02fcd256.js",
          "hash": "d0090c090fa3e336",
          "publicPath": "/assets/js/be2d6cb8.02fcd256.js"
        }
      ]
    },
    "715": {
      "js": [
        {
          "file": "assets/js/009f1e98.3a3288ef.js",
          "hash": "1ddeed66c42783af",
          "publicPath": "/assets/js/009f1e98.3a3288ef.js"
        }
      ]
    },
    "742": {
      "js": [
        {
          "file": "assets/js/aba21aa0.8ef8022b.js",
          "hash": "a78b41d2973df2d8",
          "publicPath": "/assets/js/aba21aa0.8ef8022b.js"
        }
      ]
    },
    "754": {
      "js": [
        {
          "file": "assets/js/754.30f03b23.js",
          "hash": "851200c9111457b4",
          "publicPath": "/assets/js/754.30f03b23.js"
        }
      ]
    },
    "792": {
      "js": [
        {
          "file": "assets/js/main.2f8513d6.js",
          "hash": "a9e22e9838cc75fa",
          "publicPath": "/assets/js/main.2f8513d6.js"
        }
      ]
    },
    "839": {
      "js": [
        {
          "file": "assets/js/56daa205.fae39617.js",
          "hash": "bd670b12c750d1c5",
          "publicPath": "/assets/js/56daa205.fae39617.js"
        }
      ]
    },
    "849": {
      "js": [
        {
          "file": "assets/js/0058b4c6.c81bb259.js",
          "hash": "a032ab8979b872bd",
          "publicPath": "/assets/js/0058b4c6.c81bb259.js"
        }
      ]
    },
    "854": {
      "js": [
        {
          "file": "assets/js/c98dd9d0.4dc1f193.js",
          "hash": "1451e9a0cca07e88",
          "publicPath": "/assets/js/c98dd9d0.4dc1f193.js"
        }
      ]
    },
    "869": {
      "css": [
        {
          "file": "assets/css/styles.e508cfe9.css",
          "hash": "1e9aa56c5d5c7e9d",
          "publicPath": "/assets/css/styles.e508cfe9.css"
        }
      ]
    },
    "913": {
      "js": [
        {
          "file": "assets/js/2e4bcb17.f05dd0ec.js",
          "hash": "36396a4b07769f3f",
          "publicPath": "/assets/js/2e4bcb17.f05dd0ec.js"
        }
      ]
    },
    "922": {
      "js": [
        {
          "file": "assets/js/3d44d291.77cc88e1.js",
          "hash": "cbfb536288b8ecdc",
          "publicPath": "/assets/js/3d44d291.77cc88e1.js"
        }
      ]
    },
    "924": {
      "js": [
        {
          "file": "assets/js/54f44165.5b8d460d.js",
          "hash": "71d1711facc21b94",
          "publicPath": "/assets/js/54f44165.5b8d460d.js"
        }
      ]
    },
    "976": {
      "js": [
        {
          "file": "assets/js/0e384e19.b54924f2.js",
          "hash": "9092e34bb270affa",
          "publicPath": "/assets/js/0e384e19.b54924f2.js"
        }
      ]
    }
  }
}